tropescraper/__init__.py
tropescraper/adaptors/__init__.py
tropescraper/adaptors/file_cache.py
tropescraper/adaptors/file_store.py
tropescraper/adaptors/web_page_retriever.py
tropescraper/common/__init__.py
tropescraper/common/object_factory.py
tropescraper/entities/__init__.py
tropescraper/entities/cache_information_entity.py
tropescraper/interfaces/__init__.py
tropescraper/interfaces/cache_interface.py
tropescraper/interfaces/page_parser_interface.py
tropescraper/interfaces/tropes_store_interface.py
tropescraper/interfaces/web_page_retriever_interface.py
tropescraper/use_cases/__init__.py
tropescraper/use_cases/scrape_tropes_use_case.py
tropescraper/use_cases/parsers/__init__.py
tropescraper/use_cases/parsers/tvtropes_parser.py
tropescraper-1.1.1.data/scripts/scrape-tvtropes
tropescraper-1.1.1.dist-info/LICENSE
tropescraper-1.1.1.dist-info/METADATA
tropescraper-1.1.1.dist-info/WHEEL
tropescraper-1.1.1.dist-info/top_level.txt
tropescraper-1.1.1.dist-info/RECORD
