Metadata-Version: 2.1
Name: tropescraper
Version: 1.1.1
Summary: A TvTropes scrapper
Home-page: https://github.com/rhgarcia/tropescraper
Author: rhgarcia
Author-email: 4012515+rhgarcia@users.noreply.github.com
License: LGPL
Platform: UNKNOWN
Requires-Dist: requests
Requires-Dist: lxml
Requires-Dist: cssselect
